odoo/addons/l10n_it_withholding_tax_financial_report/README.rst
odoo/addons/l10n_it_withholding_tax_financial_report/__init__.py
odoo/addons/l10n_it_withholding_tax_financial_report/__manifest__.py
odoo/addons/l10n_it_withholding_tax_financial_report/i18n/de.po
odoo/addons/l10n_it_withholding_tax_financial_report/i18n/de_DE.po
odoo/addons/l10n_it_withholding_tax_financial_report/i18n/it.po
odoo/addons/l10n_it_withholding_tax_financial_report/i18n/l10n_it_withholding_tax_financial_report.pot
odoo/addons/l10n_it_withholding_tax_financial_report/readme/CONTRIBUTORS.md
odoo/addons/l10n_it_withholding_tax_financial_report/readme/DESCRIPTION.md
odoo/addons/l10n_it_withholding_tax_financial_report/report/__init__.py
odoo/addons/l10n_it_withholding_tax_financial_report/report/open_items.py
odoo/addons/l10n_it_withholding_tax_financial_report/report/open_items_xlsx.py
odoo/addons/l10n_it_withholding_tax_financial_report/report/templates/open_items.xml
odoo/addons/l10n_it_withholding_tax_financial_report/static/description/icon.png
odoo/addons/l10n_it_withholding_tax_financial_report/static/description/index.html
odoo_addon_l10n_it_withholding_tax_financial_report-16.0.1.0.2.dist-info/METADATA
odoo_addon_l10n_it_withholding_tax_financial_report-16.0.1.0.2.dist-info/WHEEL
odoo_addon_l10n_it_withholding_tax_financial_report-16.0.1.0.2.dist-info/top_level.txt
odoo_addon_l10n_it_withholding_tax_financial_report-16.0.1.0.2.dist-info/RECORD
